composable_logs_webui/__init__.py
composable_logs_webui-0.0.16.data/data/assets/asset-manifest.json
composable_logs_webui-0.0.16.data/data/assets/favicon.ico
composable_logs_webui-0.0.16.data/data/assets/index.html
composable_logs_webui-0.0.16.data/data/assets/manifest.json
composable_logs_webui-0.0.16.data/data/assets/pdf.worker.js
composable_logs_webui-0.0.16.data/data/assets/precache-manifest.9376e4389fd0006a53f79e320af16849.js
composable_logs_webui-0.0.16.data/data/assets/service-worker.js
composable_logs_webui-0.0.16.data/data/assets/fontawesome/css/fontawesome-all.min.css
composable_logs_webui-0.0.16.data/data/assets/fontawesome/webfonts/fa-brands-400.eot
composable_logs_webui-0.0.16.data/data/assets/fontawesome/webfonts/fa-brands-400.svg
composable_logs_webui-0.0.16.data/data/assets/fontawesome/webfonts/fa-brands-400.ttf
composable_logs_webui-0.0.16.data/data/assets/fontawesome/webfonts/fa-brands-400.woff
composable_logs_webui-0.0.16.data/data/assets/fontawesome/webfonts/fa-brands-400.woff2
composable_logs_webui-0.0.16.data/data/assets/fontawesome/webfonts/fa-regular-400.eot
composable_logs_webui-0.0.16.data/data/assets/fontawesome/webfonts/fa-regular-400.svg
composable_logs_webui-0.0.16.data/data/assets/fontawesome/webfonts/fa-regular-400.ttf
composable_logs_webui-0.0.16.data/data/assets/fontawesome/webfonts/fa-regular-400.woff
composable_logs_webui-0.0.16.data/data/assets/fontawesome/webfonts/fa-regular-400.woff2
composable_logs_webui-0.0.16.data/data/assets/fontawesome/webfonts/fa-solid-900.eot
composable_logs_webui-0.0.16.data/data/assets/fontawesome/webfonts/fa-solid-900.svg
composable_logs_webui-0.0.16.data/data/assets/fontawesome/webfonts/fa-solid-900.ttf
composable_logs_webui-0.0.16.data/data/assets/fontawesome/webfonts/fa-solid-900.woff
composable_logs_webui-0.0.16.data/data/assets/fontawesome/webfonts/fa-solid-900.woff2
composable_logs_webui-0.0.16.data/data/assets/static/css/2.10c23a32.chunk.css
composable_logs_webui-0.0.16.dist-info/METADATA
composable_logs_webui-0.0.16.dist-info/WHEEL
composable_logs_webui-0.0.16.dist-info/top_level.txt
composable_logs_webui-0.0.16.dist-info/RECORD
