Metadata-Version: 2.1
Name: composable-logs-webui
Version: 0.0.16
Summary: This Python package contain compiled web assets for a fork of the MLFlow front end.It is modified so that it can be deployed as a static website without a backend.
Home-page: https://composable-logs.github.io/composable-logs/
Author: Matias Dahl (based on a modified version of the MLFlow project)
Author-email: matias.dahl@iki.fi
License: Various, see the description
Platform: UNKNOWN
